{"is_source_file": false, "format": "", "description": "", "external_files": [], "external_methods": [], "published": [], "classes": [], "methods": [], "calls": [], "search-terms": ["CSS", "theme", "dark", "light", "App", "toggle"], "state": 2, "file_id": 5, "knowledge_revision": 14, "git_revision": "04977f51f58e7dbfebbe4ac2c90ddfba4156dd30", "hash": "22f9e17cc1848b56dbb244518ac2707e", "format-version": 4, "code-base-name": "bmi_calculator_frontend", "filename": "bmi_calculator_frontend/src/App.css", "revision_history": [{"14": "04977f51f58e7dbfebbe4ac2c90ddfba4156dd30"}]}